sasa/__init__.py
sasa/applications/__init__.py
sasa/applications/codes.py
sasa/email/__init__.py
sasa/email/send_email.py
sasa/notifications/__init__.py
sasa/notifications/notification.py
sasa/sms/__init__.py
sasa/sms/manager.py
sasa/tasks/__init__.py
sasa/tasks/result.py
sasa/tasks/severity.py
sasacommon-0.1.1.dist-info/LICENSE.txt
sasacommon-0.1.1.dist-info/METADATA
sasacommon-0.1.1.dist-info/WHEEL
sasacommon-0.1.1.dist-info/top_level.txt
sasacommon-0.1.1.dist-info/RECORD
